SIRVsuite/SIRVsuite.py
SIRVsuite/__init__.py
SIRVsuite/__main__.py
SIRVsuite/_version.py
SIRVsuite/Pipeline/__init__.py
SIRVsuite/Pipeline/countReader.py
SIRVsuite/Pipeline/helper.py
SIRVsuite/Pipeline/Concentration/SIRV_concentration.py
SIRVsuite/Pipeline/Concentration/__init__.py
SIRVsuite/Pipeline/Correlation/ERCC_correlation.py
SIRVsuite/Pipeline/Correlation/__init__.py
SIRVsuite/Pipeline/Coverage/SIRVset_coverage.py
SIRVsuite/Pipeline/Coverage/__init__.py
SIRVsuite/Pipeline/Coverage/cairoDrawer.py
SIRVsuite/Resources/ERCC92_Concentration.tsv
SIRVsuite/Resources/SIRV_isoforms_multi-fasta-annotation_190418a.gtf
SIRVsuite/Resources/SIRV_isoforms_multi-fasta_190418a.fasta
SIRVsuite/Resources/SIRV_isoforms_multi-fasta_190418a.fasta.fai
SIRVsuite/Resources/igv_session.xml
SIRVsuite-0.1.3.dist-info/AUTHORS.rst
SIRVsuite-0.1.3.dist-info/LICENCE
SIRVsuite-0.1.3.dist-info/METADATA
SIRVsuite-0.1.3.dist-info/WHEEL
SIRVsuite-0.1.3.dist-info/entry_points.txt
SIRVsuite-0.1.3.dist-info/top_level.txt
SIRVsuite-0.1.3.dist-info/RECORD
