Metadata-Version: 2.1
Name: SIRVsuite
Version: 0.1.3
Summary: SIRVsuite - a command line tool to QC an RNA-Seq workflow using Lexogen's SIRV spike-in controls
Author-email: Tomas Drozd <tomas.drozd@lexogen.com>, Andreas Tuerk <andreas.tuerk@lexogen.com>
License: Software License
Project-URL: Source, https://github.com/Lexogen-Tools/SIRVsuite/
Project-URL: Documentation, https://github.com/Lexogen-Tools/SIRVsuite/blob/master/README.md
Classifier: Development Status :: 3 - Alpha
Classifier: Intended Audience :: Science/Research
Classifier: Topic :: Scientific/Engineering :: Bio-Informatics
Classifier: Natural Language :: English
Classifier: Programming Language :: Python :: 3.8
Classifier: Programming Language :: Python :: 3.9
Classifier: Programming Language :: Python :: 3.10
Classifier: Programming Language :: Python :: 3.11
Classifier: License :: Other/Proprietary License
Requires-Python: >=3.8
License-File: LICENCE
License-File: AUTHORS.rst
Requires-Dist: contourpy
Requires-Dist: cycler>=0.10.0
Requires-Dist: fonttools
Requires-Dist: gtfparse>=1.2.1
Requires-Dist: kiwisolver>=1.2.0
Requires-Dist: matplotlib<4.0.0,>=3.3.1
Requires-Dist: numpy<=1.26.4,>=1.19.2
Requires-Dist: packaging~=24.1
Requires-Dist: pandas<=1.5.3,>=1.1.3
Requires-Dist: pillow
Requires-Dist: polars
Requires-Dist: pyarrow
Requires-Dist: pyBigWig>=0.3.18
Requires-Dist: pycairo>=1.20
Requires-Dist: pyparsing>=2.4.7
Requires-Dist: pysam>=0.16
Requires-Dist: python-dateutil>=2.8.1
Requires-Dist: pytz>=2020.1
Requires-Dist: scipy>=1.5.2
Requires-Dist: six>=1.15.0
Requires-Dist: tzdata
